ros2_graph/__init__.py
ros2_graph/__main__.py
ros2_graph/graph_generator.py
ros2_graph/ros_cli_utils.py
ros2_graph/ros_element.py
ros2_graph-0.0.5.dist-info/LICENSE
ros2_graph-0.0.5.dist-info/METADATA
ros2_graph-0.0.5.dist-info/WHEEL
ros2_graph-0.0.5.dist-info/entry_points.txt
ros2_graph-0.0.5.dist-info/top_level.txt
ros2_graph-0.0.5.dist-info/RECORD
