Metadata-Version: 2.1
Name: ros2-graph
Version: 0.0.5
Summary: Generate mermaid description of ROS2 graphs to add on your markdown files.
Home-page: https://github.com/kiwicampus/ros2_graph
License-File: LICENSE
Requires-Dist: argparse (~=1.4.0)
Requires-Dist: pyyaml (~=6.0)
